evergreen_lint/__init__.py
evergreen_lint/__main__.py
evergreen_lint/config.py
evergreen_lint/config_with_bad_yaml.yml
evergreen_lint/helpers.py
evergreen_lint/model.py
evergreen_lint/rules/__init__.py
evergreen_lint/rules/commonsense.py
evergreen_lint/rules/dependency_for_func.py
evergreen_lint/rules/enforce_tags_for_tasks.py
evergreen_lint/rules/enforce_tags_for_variants.py
evergreen_lint/rules/enforce_tasks_distro_with_special_tag.py
evergreen_lint/rules/forbid_tasks_with_tag_on_variants.py
evergreen_lint/rules/invalid_build_parameter.py
evergreen_lint/rules/required_expansions_write.py
evergreen_lint/rules/tasks_for_variants.py
evergreen_lint/rules/variant_expansions.py
evergreen_lint/yamlhandler.py
evergreen_lint-0.1.10.dist-info/METADATA
evergreen_lint-0.1.10.dist-info/WHEEL
evergreen_lint-0.1.10.dist-info/entry_points.txt
evergreen_lint-0.1.10.dist-info/RECORD
