Metadata-Version: 2.3
Name: evergreen-lint
Version: 0.1.10
Summary: 
Author: DevProd Build Team
Author-email: devprod-build-team@mongodb.com
Requires-Python: >=3.9,<4.0
Classifier: Programming Language :: Python :: 3
Classifier: Programming Language :: Python :: 3.9
Classifier: Programming Language :: Python :: 3.10
Classifier: Programming Language :: Python :: 3.11
Classifier: Programming Language :: Python :: 3.12
Classifier: Programming Language :: Python :: 3.13
Requires-Dist: PyYAML (>=3.0.0)
Requires-Dist: click (>=7.0)
Requires-Dist: typing-extensions (>=3.10.0)
